csr_proxy/__init__.py
csr_proxy/api.py
csr_proxy/cli.py
csr_proxy/config.py
csr_proxy/log.py
csr_proxy/py.typed
csr_proxy-0.1.0.dist-info/LICENSE.md
csr_proxy-0.1.0.dist-info/METADATA
csr_proxy-0.1.0.dist-info/WHEEL
csr_proxy-0.1.0.dist-info/entry_points.txt
csr_proxy-0.1.0.dist-info/top_level.txt
csr_proxy-0.1.0.dist-info/RECORD
