Metadata-Version: 2.1
Name: csr-proxy
Version: 0.1.0
Author: Gufo Labs
License: BSD 3-Clause License
Project-URL: Bug Tracker, https://github.com/gufolabs/csr_proxy/issues
Project-URL: Changelog, https://github.com/gufolabs/csr_proxy/blob/master/CHANGELOG.md
Project-URL: Documentation, https://docs.gufolabs.com/csr_proxy/
Project-URL: Homepage, https://github.com/gufolabs/csr_proxy/
Project-URL: Source Code, https://github.com/gufolabs/csr_proxy/
Keywords: ACME,CSR,Proxy
Classifier: Development Status :: 5 - Production/Stable
Classifier: Intended Audience :: Developers
Classifier: Programming Language :: Python :: 3.8
Classifier: Programming Language :: Python :: 3.9
Classifier: Programming Language :: Python :: 3.10
Classifier: Programming Language :: Python :: 3.11
Classifier: Programming Language :: Python :: 3.12
Classifier: License :: OSI Approved :: BSD License
Classifier: Topic :: Software Development
Classifier: Topic :: Software Development :: Libraries
Classifier: Topic :: Software Development :: Libraries :: Python Modules
Classifier: Operating System :: OS Independent
Classifier: Typing :: Typed
Requires-Python: >=3.8
License-File: LICENSE.md
Requires-Dist: gufo-acme ==0.2.0
Requires-Dist: starlette ==0.32.0
Requires-Dist: uvicorn ==0.24.0
